helpbutton.py
helpbutton-1.0.5.dist-info/WHEEL
helpbutton-1.0.5.dist-info/METADATA
helpbutton-1.0.5.dist-info/RECORD
